puZC
